my_minipackzpalfi/__init__.py
my_minipackzpalfi/ft_progress.py
my_minipackzpalfi/log.py
my_minipackzpalfi-0.0.11.dist-info/LICENCE
my_minipackzpalfi-0.0.11.dist-info/METADATA
my_minipackzpalfi-0.0.11.dist-info/WHEEL
my_minipackzpalfi-0.0.11.dist-info/top_level.txt
my_minipackzpalfi-0.0.11.dist-info/RECORD
